{
    "AE": [
        {
            "executionStatus": "success",
            "dataset": "ae.xpt",
            "domain": "AE",
            "variables": [
                "AESMIE",
                "QNAM"
            ],
            "message": "Missing AESMIE=Y where SUPPAE.QNAM=AESOSP",
            "errors": [
                {
                    "value": {
                        "AESMIE": "",
                        "QNAM": "AESOSP"
                    },
                    "row": 6,
                    "USUBJID": "CDISC-TEST-001",
                    "SEQ": 1
                },
                {
                    "value": {
                        "AESMIE": "N",
                        "QNAM": "AESOSP"
                    },
                    "row": 73,
                    "USUBJID": "CDISC-TEST-002",
                    "SEQ": 29
                }
            ]
        }
    ],
    "SUPPAE": [
        {
            "executionStatus": "skipped",
            "dataset": null,
            "domain": "SUPPAE",
            "variables": [],
            "message": null,
            "errors": []
        }
    ]
}