{
  "LB": [
    {
      "executionStatus": "execution_error",
      "domain": "LB",
      "variables": [],
      "message": "rule execution error",
      "errors": [
        {
          "error": "Column not found in data",
          "message": "LBTPTNUM"
        }
      ]
    }
  ],
  "PC": [
    {
      "executionStatus": "execution_error",
      "domain": "PC",
      "variables": [],
      "message": "rule execution error",
      "errors": [
        {
          "error": "Column not found in data",
          "message": "PCTPTNUM"
        }
      ]
    }
  ]
}