{5 items
"LB":[1 item
0:{6 items
"executionStatus":"success"
"dataset":"lb.xpt"
"domain":"LB"
"variables":[]0 items
"message":NULL
"errors":[]0 items
}
]
"OE":[1 item
0:{6 items
"executionStatus":"success"
"dataset":"oe.xpt"
"domain":"OE"
"variables":[]0 items
"message":NULL
"errors":[]0 items
}
]
"SV":[1 item
0:{6 items
"executionStatus":"skipped"
"dataset":"sv.xpt"
"domain":"SV"
"variables":[]0 items
"message":"Rule skipped - doesn't apply to domain for rule id=CORE-000168, dataset=SV"
"errors":[]0 items
}
]
"TV":[1 item
0:{6 items
"executionStatus":"execution_error"
"dataset":"tv.xpt"
"domain":"TV"
"variables":[]0 items
"message":"rule execution error"
"errors":[1 item
0:{3 items
"dataset":"tv.xpt"
"error":"Column not found in data"
"message":"USUBJID"
}
]
}
]
"VS":[1 item
0:{6 items
"executionStatus":"success"
"dataset":"vs.xpt"
"domain":"VS"
"variables":[]0 items
"message":NULL
"errors":[]0 items
}
]
}