{
  "DM": [
    {
      "executionStatus": "success",
      "dataset": "dm.xpt",
      "domain": "DM",
      "variables": [
        "DTHDTC"
      ],
      "message": "DTHDTC must not be present in SEND dataset",
      "errors": [
        {
          "value": {
            "DTHDTC": ""
          }
        }
      ]
    }
  ],
  "TX": [
    {
      "executionStatus": "skipped",
      "dataset": null,
      "domain": "TX",
      "variables": [],
      "message": null,
      "errors": []
    }
  ],
  "VS": [
    {
      "executionStatus": "skipped",
      "dataset": null,
      "domain": "VS",
      "variables": [],
      "message": null,
      "errors": []
    }
  ]
}