{2 items
"SV":[1 item
0:{5 items
"executionStatus":"success"
"domain":"SV"
"variables":[3 items
0:"$vis_list"
1:"SVUPDES"
2:"VISIT"
]
"message":"SV.VISIT value must be present in TV.VISIT when SVUPDES is null"
"errors":[2 items
0:{3 items
"value":{3 items
"$vis_list":[14 items
0:"SCREENING 2"
1:"WEEK 20"
2:"WEEK 2"
3:"EARLY DISCONTINUATION RETRIEVAL"
4:"WEEK 12"
5:"WEEK 26"
6:"WEEK 8"
7:"WEEK 6"
8:"EARLY DISCONTINUATION"
9:"WEEK 24"
10:"WEEK 16"
11:"SCREENING 1"
12:"WEEK 4"
13:"BASELINE"
]
"SVUPDES":""
"VISIT":""
}
"row":10
"USUBJID":"CDISC001"
}
1:{3 items
"value":{3 items
"$vis_list":[14 items
0:"SCREENING 2"
1:"WEEK 20"
2:"WEEK 2"
3:"EARLY DISCONTINUATION RETRIEVAL"
4:"WEEK 12"
5:"WEEK 26"
6:"WEEK 8"
7:"WEEK 6"
8:"EARLY DISCONTINUATION"
9:"WEEK 24"
10:"WEEK 16"
11:"SCREENING 1"
12:"WEEK 4"
13:"BASELINE"
]
"SVUPDES":""
"VISIT":"UNSCHEDULED"
}
"row":16
"USUBJID":"CDISC002"
}
]
}
]
"TV":[1 item
0:{5 items
"executionStatus":"skipped"
"domain":"TV"
"variables":[]0 items
"message":NULL
"errors":[]0 items
}
]
}